sinetstreamplugin/compression/lz4.py
sinetstream_comp_lz4-1.9.2.dist-info/METADATA
sinetstream_comp_lz4-1.9.2.dist-info/WHEEL
sinetstream_comp_lz4-1.9.2.dist-info/entry_points.txt
sinetstream_comp_lz4-1.9.2.dist-info/RECORD
