Metadata-Version: 2.4
Name: sinetstream-comp-lz4
Version: 1.9.2
Summary: LZ4 compression plugin for SINETStream library
Project-URL: Documentation, https://www.sinetstream.net/
Project-URL: Repository, https://github.com/nii-gakunin-cloud/sinetstream.git
License: Apache License, Version 2.0
Classifier: Intended Audience :: Developers
Classifier: License :: OSI Approved :: Apache Software License
Classifier: Programming Language :: Python :: 3 :: Only
Classifier: Topic :: Software Development :: Libraries :: Python Modules
Requires-Python: >=3.9
Requires-Dist: lz4
Requires-Dist: sinetstream>=1.8.1; python_version < '3.12'
Requires-Dist: sinetstream>=1.8.2; python_version >= '3.12'
